ghostvision/__init__.py
ghostvision/__main__.py
ghostvision/class_crabObj_rf.py
ghostvision/detect.py
ghostvision/main_crabDetect.py
ghostvision/version.py
ghostvision-1.0.0b5.data/data/ghostvision_config/default_params.json
ghostvision-1.0.0b5.dist-info/METADATA
ghostvision-1.0.0b5.dist-info/WHEEL
ghostvision-1.0.0b5.dist-info/top_level.txt
ghostvision-1.0.0b5.dist-info/RECORD
