Metadata-Version: 2.4
Name: ghostvision
Version: 1.0.0b5
Summary: Near-real time detection of derelict (ghost) crab pots with side-scan sonar.
Author: Cameron Bodine
Author-email: bodine.cs@gmail.email
Project-URL: Issues, https://github.com/PINGEcosystem/GhostVision/issues
Project-URL: GitHub, https://github.com/PINGEcosystem/GhostVision
Keywords: pingmapper,sonar,ecology,remotesensing,sidescan,sidescan-sonar,aquatic,humminbird,lowrance,gis,oceanography,limnology,object-detection
Classifier: Development Status :: 4 - Beta
Classifier: Programming Language :: Python :: 3
Classifier: License :: OSI Approved :: MIT License
Classifier: Operating System :: OS Independent
Classifier: Topic :: Scientific/Engineering
Classifier: Topic :: Scientific/Engineering :: Visualization
Classifier: Topic :: Scientific/Engineering :: Oceanography
Classifier: Topic :: Scientific/Engineering :: GIS
Classifier: Topic :: Scientific/Engineering :: Hydrology
Requires-Python: >=3.6
Requires-Dist: pinginstaller
Requires-Dist: pingwizard
Requires-Dist: pingverter
Requires-Dist: pingmapper
Requires-Dist: pingdetect
Dynamic: author
Dynamic: author-email
Dynamic: classifier
Dynamic: description
Dynamic: description-content-type
Dynamic: keywords
Dynamic: project-url
Dynamic: requires-dist
Dynamic: requires-python
Dynamic: summary
